epic.py
epic_by_tom_tkacz-1.0.0.dist-info/LICENSE.txt
epic_by_tom_tkacz-1.0.0.dist-info/METADATA
epic_by_tom_tkacz-1.0.0.dist-info/WHEEL
epic_by_tom_tkacz-1.0.0.dist-info/top_level.txt
epic_by_tom_tkacz-1.0.0.dist-info/RECORD
