Metadata-Version: 2.1
Name: epic-by-tom-tkacz
Version: 1.0.0
Home-page: https://github.com/TomTkacz/epic
Author: Tom Tkacz
Author-email: thomasatkacz@gmail.com
Classifier: Programming Language :: Python
Classifier: Programming Language :: Python :: 3
Classifier: License :: OSI Approved :: MIT License
Classifier: Operating System :: OS Independent
License-File: LICENSE.txt
Provides-Extra: dev
Requires-Dist: pytest (>=3.7) ; extra == 'dev'
